coord_operation/__init__.py
coord_operation/operation.py
coord_operation/surface.py
coord_operation/math_util/__init__.py
coord_operation/math_util/integral.py
coord_operation/projection/__init__.py
coord_operation/projection/epsg.py
coord_operation/projection/map_projections.py
coord_operation/projection/mercator_spherical.py
coord_operation-0.16.0.dist-info/LICENSE.md
coord_operation-0.16.0.dist-info/METADATA
coord_operation-0.16.0.dist-info/WHEEL
coord_operation-0.16.0.dist-info/top_level.txt
coord_operation-0.16.0.dist-info/RECORD
